build/lib/pySNOM/__init__.py
build/lib/pySNOM/defaults.py
build/lib/pySNOM/images.py
build/lib/pySNOM/interferograms.py
build/lib/pySNOM/readers.py
build/lib/pySNOM/spectra.py
build/lib/pySNOM/tests/__init__.py
build/lib/pySNOM/tests/test_interferograms.py
build/lib/pySNOM/tests/test_readers.py
build/lib/pySNOM/tests/test_spectra.py
build/lib/pySNOM/tests/test_transform.py
conda/meta.yaml
pySNOM/__init__.py
pySNOM/defaults.py
pySNOM/images.py
pySNOM/interferograms.py
pySNOM/readers.py
pySNOM/spectra.py
pySNOM/datasets/neafile_test_ifg.nea
pySNOM/datasets/testPsHet O3A raw.gsf
pySNOM/datasets/testPsHetData.gwy
pySNOM/datasets/testifg_multipoints.txt
pySNOM/datasets/testifg_singlepoint.txt
pySNOM/datasets/testinfofile.txt
pySNOM/datasets/testspectrum_multipoint.txt
pySNOM/datasets/testspectrum_nanoraman.txt
pySNOM/datasets/testspectrum_singlepoint.txt
pySNOM/datasets/testspectrum_singlepoint_ref.txt
pySNOM/examples/imageprocess.ipynb
pySNOM/examples/spectrumprocess.ipynb
pySNOM/examples/tests_for_tests.ipynb
pySNOM/tests/__init__.py
pySNOM/tests/test_interferograms.py
pySNOM/tests/test_readers.py
pySNOM/tests/test_spectra.py
pySNOM/tests/test_transform.py
pysnom-0.3.0.dist-info/licenses/LICENSE
pysnom-0.3.0.dist-info/METADATA
pysnom-0.3.0.dist-info/WHEEL
pysnom-0.3.0.dist-info/top_level.txt
pysnom-0.3.0.dist-info/RECORD
