Metadata-Version: 2.4
Name: pySNOM
Version: 0.3.0
Summary: Python tools for SNOM data processing.
Author-email: Gergely Németh <ngergihun@gmail.com>, Ferenc Borondics <borondics.accounts@gmail.com>, Marko Toplak <marko.toplak@gmail.com>
Maintainer-email: Gergely Németh <ngergihun@gmail.com>
License: This program is free software distributed under the Attribution-NonCommercial-ShareAlike 4.0 (CC BY-NC-SA 4.0).
Project-URL: Homepage, https://github.com/Quasars/pySNOM
Project-URL: Bug Reports, https://github.com/Quasars/pySNOM/issues
Project-URL: Source, https://github.com/Quasars/pySNOM/
Keywords: snom,near-field,data processing
Classifier: Development Status :: 3 - Alpha
Classifier: Intended Audience :: Science/Research
Classifier: Programming Language :: Python :: 3
Requires-Python: >=3.10
License-File: LICENSE
Requires-Dist: gwyfile>=0.2.0
Requires-Dist: numpy<2.3.0,>=1.24.0
Requires-Dist: setuptools
Requires-Dist: scipy
Requires-Dist: gsffile
Requires-Dist: pandas>=1.4.0
Requires-Dist: scikit-image
Dynamic: license-file
